mypackage/__init__.py
mypackage/hello.py
mypackage_prashant_chouhan-0.1.0.dist-info/licenses/LICENSE
mypackage_prashant_chouhan-0.1.0.dist-info/METADATA
mypackage_prashant_chouhan-0.1.0.dist-info/WHEEL
mypackage_prashant_chouhan-0.1.0.dist-info/top_level.txt
mypackage_prashant_chouhan-0.1.0.dist-info/RECORD
