Metadata-Version: 2.4
Name: mypackage-prashant-Chouhan
Version: 0.1.0
Summary: A tiny example package (PoC)
Author-email: Prashant Chouhan <prashantchouhan771@gmail.com>
License: MIT
Requires-Python: >=3.8
License-File: LICENSE
Dynamic: license-file
